{
  "target_distance_m": 20.0,
  "dvl_estimated_distance_m": 20.004746406161622,
  "pose_forward_displacement_m": 19.97437286376953,
  "pose_ground_truth_displacement_m": 20.90069140771996,
  "longitudinal_error_m": -0.02562713623046875,
  "absolute_longitudinal_error_m": 0.02562713623046875,
  "signed_error_m": 0.030373542392091224,
  "absolute_distance_error_m": 0.030373542392091224,
  "percentage_error": 0.15206255835538246,
  "lateral_drift_m": 6.153318618424237,
  "final_position_error_m": 6.153371983714111,
  "duration_s": 48.9820150999999,
  "num_samples": 1470,
  "stop_reason": "target_reached",
  "target_reached": true,
  "forward_command": 2.0,
  "forward_command_vector": [
    0.0,
    0.0,
    0.0,
    0.0,
    2.0,
    2.0,
    2.0,
    2.0
  ],
  "old_forward_command_default": 12.0,
  "new_forward_command_default": 2.0,
  "dvl_forward_index": 0,
  "dvl_forward_sign": 1.0,
  "warmup_ticks": 10,
  "elapsed_wall_clock_time_s": 48.98212850000027,
  "time_source": "wall_clock",
  "dt_source": "wall_clock",
  "mean_dt": 0.03334378155207617,
  "std_dt": 0.0001452652085388231,
  "dt_fallback_count": 0,
  "speed_warning_threshold_mps": 1.0,
  "max_dvl_speed_warning_threshold_mps": 1.5,
  "mean_dvl_forward_velocity_mps": 0.40812534193997746,
  "max_dvl_forward_velocity_mps": 0.5408575534820557,
  "average_dvl_speed_mps": 0.40841003305643225,
  "average_pose_speed_mps": 0.4267013385433382,
  "mean_speed_mps": 0.4267013385433382,
  "initial_pose": {
    "x": 0.0,
    "y": 0.008119369857013226,
    "z": -4.0
  },
  "final_pose": {
    "x": 19.97437286376953,
    "y": 6.16143798828125,
    "z": -4.0
  },
  "distance_validation_warnings": [],
  "diagnostic_distance_check": false,
  "experiment_label": "Step 2C comparison no-compensation",
  "current_x": 0.0,
  "current_y": 1.0,
  "current_z": 0.0,
  "current_magnitude": 1.0,
  "current_api_method": "env.set_ocean_currents(agent_name, velocity)",
  "current_application_mode": "every_step",
  "current_application_calls": 1480,
  "final_lateral_offset": 6.153318618424237,
  "summary_title": "Step 2C comparison no-compensation summary",
  "output_dir": "C:\\Users\\andrea.bedei3\\Desktop\\HoloMotion\\results\\step_02c_pi_compensation_comparison\\20260515_111553\\target_20m_current_y_1_rep_03_no_compensation",
  "dvl_pose_sanity_check": {
    "dvl_estimated_distance_m": 20.004746406161622,
    "pose_forward_displacement_m": 19.97437286376953,
    "lateral_drift_m": 6.153318618424237,
    "lateral_drift_ratio": 0.30806066655466413,
    "opposite_signs": false,
    "warning": ""
  },
  "current_warning": "",
  "target_distance": 20.0,
  "dvl_estimated_distance": 20.004746406161622,
  "pose_forward_displacement": 19.97437286376953,
  "pose_euclidean_displacement": 20.90069140771996,
  "longitudinal_error": -0.02562713623046875,
  "absolute_longitudinal_error": 0.02562713623046875,
  "absolute_error": 0.030373542392091224,
  "lateral_drift": 6.153318618424237,
  "final_position_error": 6.153371983714111,
  "duration": 48.9820150999999,
  "sample_count": 1470,
  "average_pose_speed": 0.4267013385433382,
  "max_dvl_forward_velocity": 0.5408575534820557,
  "mean_dvl_forward_velocity": 0.40812534193997746
}
